opera_cloud_mcp/__init__.py
opera_cloud_mcp/__main__.py
opera_cloud_mcp/cli.py
opera_cloud_mcp/main.py
opera_cloud_mcp/server.py
opera_cloud_mcp/auth/__init__.py
opera_cloud_mcp/auth/audit_logger.py
opera_cloud_mcp/auth/audit_sqlmodel.py
opera_cloud_mcp/auth/oauth_handler.py
opera_cloud_mcp/auth/secure_oauth_handler.py
opera_cloud_mcp/auth/security_enhancements.py
opera_cloud_mcp/auth/security_middleware.py
opera_cloud_mcp/clients/__init__.py
opera_cloud_mcp/clients/base_client.py
opera_cloud_mcp/clients/base_client_refactored.py
opera_cloud_mcp/clients/client_factory.py
opera_cloud_mcp/clients/api_clients/__init__.py
opera_cloud_mcp/clients/api_clients/activities.py
opera_cloud_mcp/clients/api_clients/block.py
opera_cloud_mcp/clients/api_clients/cashiering.py
opera_cloud_mcp/clients/api_clients/crm.py
opera_cloud_mcp/clients/api_clients/front_office.py
opera_cloud_mcp/clients/api_clients/housekeeping.py
opera_cloud_mcp/clients/api_clients/inventory.py
opera_cloud_mcp/clients/api_clients/rates.py
opera_cloud_mcp/clients/api_clients/reservations.py
opera_cloud_mcp/config/__init__.py
opera_cloud_mcp/config/security_settings.py
opera_cloud_mcp/config/settings.py
opera_cloud_mcp/models/__init__.py
opera_cloud_mcp/models/common.py
opera_cloud_mcp/models/financial.py
opera_cloud_mcp/models/guest.py
opera_cloud_mcp/models/reservation.py
opera_cloud_mcp/models/room.py
opera_cloud_mcp/resources/__init__.py
opera_cloud_mcp/resources/api_specs.py
opera_cloud_mcp/resources/health_check.py
opera_cloud_mcp/tools/__init__.py
opera_cloud_mcp/tools/financial_tools.py
opera_cloud_mcp/tools/guest_tools.py
opera_cloud_mcp/tools/operation_tools.py
opera_cloud_mcp/tools/reservation_tools.py
opera_cloud_mcp/tools/room_tools.py
opera_cloud_mcp/tools/tool_registry.py
opera_cloud_mcp/utils/__init__.py
opera_cloud_mcp/utils/cache_manager.py
opera_cloud_mcp/utils/client_factory.py
opera_cloud_mcp/utils/connection_optimizer.py
opera_cloud_mcp/utils/exceptions.py
opera_cloud_mcp-0.3.4.dist-info/METADATA
opera_cloud_mcp-0.3.4.dist-info/WHEEL
opera_cloud_mcp-0.3.4.dist-info/entry_points.txt
opera_cloud_mcp-0.3.4.dist-info/licenses/LICENSE
opera_cloud_mcp-0.3.4.dist-info/RECORD
